autogam/autogam.py
autogam-0.1.0.dist-info/LICENSE
autogam-0.1.0.dist-info/METADATA
autogam-0.1.0.dist-info/WHEEL
autogam-0.1.0.dist-info/RECORD
