Metadata-Version: 2.3
Name: autogam
Version: 0.1.0
Summary: Automate the Creation of Generalized Additive Models (GAMs)
License: MIT
Author: Chitu Okoli
Requires-Python: >=3.12
Classifier: License :: OSI Approved :: MIT License
Classifier: Programming Language :: Python :: 3
Classifier: Programming Language :: Python :: 3.12
Classifier: Programming Language :: Python :: 3.13
Requires-Dist: numpy (>=2.2.2)
Requires-Dist: pandas (>=2.2.3)
Requires-Dist: statsmodels (>=0.14.4)
